bs42frame/README.MD
bs42frame/__init__.py
bs42frame/requirements.txt
bs42frame/thirdparty.json
bs42frame-0.10.dist-info/LICENSE.rst
bs42frame-0.10.dist-info/METADATA
bs42frame-0.10.dist-info/WHEEL
bs42frame-0.10.dist-info/top_level.txt
bs42frame-0.10.dist-info/RECORD
